{
    "SleekLady B1": "MERU",
    "SleekLady B2": "MOMBASA/DIGO RD",
    "SleekLady B3": "KARATINA",
    "SleekLady B4": "NAIROBI/RIVER ROAD",
    "SleekLady B5": "NAIROBI/RONALD NGALA",
    "SleekLady B6": "ELDORET/OLOO STRT",
    "SleekLady B7": "NAKURU/MBURU GICHUA RD",
    "SleekLady B8": "NAIROBI/MOI AVENUE",
    "SleekLady B9": "MOMBASA/DIGO RD",
    "SleekLady B10": "THIKA/COMMERCIAL STRT",
    "SleekLady B11": "MTWAPA",
    "SleekLady B12": "ELDORET/OGINGA RD",
    "SleekLady B13": "NYERI",
    "SleekLady B14": "MOMBASA/DIGO RD",
    "SleekLady B15": "MAUA",
    "SleekLady B16": "NAKURU TRANSFERRED TO MERU",
    "SleekLady B17": "NAKURU/GUSII STRT",
    "SleekLady B18": "KITALE",
    "SleekLady B19": "TOM MBOYA",
    "SleekLady B20": "THIKA/UHURU STRT",
    "SleekLady B21": "KITUI",
    "SleekLady B22": "BUNGOMA",
    "SleekLady B23": "MACHAKOS",
    "SleekLady B24": "KISII",
    "SleekLady B25": "NANYUKI",
    "SleekLady B26": "KITENGELA",
    "SleekLady B27": "KERCHIO",
    "SleekLady B28": "RONGAI",
    "SleekLady B29": "KAWANGWARE",
    "SleekLady B30": "MIGORI",
    "SleekLady B31": "TOM MBOYA",
    "SleekLady B32": "TOM MBOYA",
    "SleekLady B33": "NAIROBI/MKU",
    "SleekLady B34": "KAKAMEGA",
    "SleekLady B35": "THIKA",
    "SleekLady B36": "ELDORET",
    "SleekLady B37": "MLOLONGO",
    "SleekLady B38": "KISUMU"
}
